atomac/AXCallbacks.py
atomac/AXClasses.py
atomac/AXKeyCodeConstants.py
atomac/AXKeyboard.py
atomac/AppHelper.py
atomac/Clipboard.py
atomac/Prefs.py
atomac/__init__.py
atomac/_a11y.so
atomac/version.py
atomac/ldtp/__init__.py
atomac/ldtp/client.py
atomac/ldtp/client_exception.py
atomac/ldtp/log.py
atomac/ldtp/state.py
atomac/ldtpd/__init__.py
atomac/ldtpd/combo_box.py
atomac/ldtpd/constants.py
atomac/ldtpd/core.py
atomac/ldtpd/generic.py
atomac/ldtpd/keypress_actions.py
atomac/ldtpd/menu.py
atomac/ldtpd/mouse.py
atomac/ldtpd/page_tab_list.py
atomac/ldtpd/server_exception.py
atomac/ldtpd/table.py
atomac/ldtpd/test.py
atomac/ldtpd/text.py
atomac/ldtpd/utils.py
atomac/ldtpd/value.py
atomac/ooldtp/__init__.py
atomac/ooldtp/client_exception.py
atomac/ooldtp/log.py
atomac/ooldtp/state.py
pyatomac-2.0.7.dist-info/METADATA
pyatomac-2.0.7.dist-info/RECORD
pyatomac-2.0.7.dist-info/WHEEL
pyatomac-2.0.7.dist-info/entry_points.txt
pyatomac-2.0.7.dist-info/top_level.txt
