Metadata-Version: 1.1
Name: pyatomac
Version: 2.0.7
Summary: Automated Testing on Mac - test GUI applications written in Cocoa by using Apple's Accessibility API
Home-page: https://github.com/alex-kostirin/pyatomac
Author: Alexey Kostyrin
Author-email: Alexey.Kostyrin@kaspersky.com
License: GPLv2
Platform: UNKNOWN
Classifier: Development Status :: 5 - Production/Stable
Classifier: Environment :: MacOS X :: Cocoa
Classifier: License :: OSI Approved :: GNU General Public License (GPL)
Classifier: Topic :: Software Development :: Quality Assurance
Classifier: Topic :: Software Development :: Testing
